{
  "generator-jhipster": {
    "promptValues": {
      "packageName": "com.ifuture.haipin",
      "nativeLanguage": "zh-cn"
    },
    "jhipsterVersion": "4.6.1",
    "baseName": "haipin",
    "packageName": "com.ifuture.haipin",
    "packageFolder": "com/ifuture/haipin",
    "serverPort": "8080",
    "authenticationType": "jwt",
    "hibernateCache": "ehcache",
    "clusteredHttpSession": false,
    "websocket": false,
    "databaseType": "sql",
    "devDatabaseType": "h2Disk",
    "prodDatabaseType": "mysql",
    "searchEngine": false,
    "messageBroker": false,
    "serviceDiscoveryType": false,
    "buildTool": "maven",
    "enableSocialSignIn": false,
    "jwtSecretKey": "2405ff0eeb1d11ea23787ea4464eb9479e629e4d",
    "clientFramework": "angularX",
    "useSass": true,
    "clientPackageManager": "yarn",
    "applicationType": "monolith",
    "testFrameworks": [],
    "jhiPrefix": "jhi",
    "enableTranslation": true,
    "nativeLanguage": "zh-cn",
    "languages": [
      "zh-cn",
      "en"
    ]
  }
}